{
  "motivul_prezentarii": "Durere genunchi drept apărută după cădere de la melțime, cu trosnet la impact, de aproximativ o săptămână",
  "evaluarea_durerii_vas": null,
  "localizarea_durerii": [
    "genunchi_dr"
  ],
  "localizarea_durerii_alta": null,
  "antecedente": [],
  "antecedente_altele": null,
  "medicatie_actuala": [],
  "evaluare_functionala_initiala": "Diagnostic: inflamație menință și ligament colateral-lateral genunchi drept; posibil fractură non-displasivă.\nObiective terapeutice: reducerea inflamației, refacerea mobilității articulare, recomandare radiografie."
}
