{
  "motivul_prezentarii": "durere la genunchiul drept și glezna dreaptă, apărută treptat în ultimele săptămâni, în context de volan",
  "evaluarea_durerii_vas": 0,
  "localizarea_durerii": [
    "genunchi_dr",
    "glezna_dr"
  ],
  "localizarea_durerii_alta": null,
  "antecedente": [],
  "antecedente_altele": "astm bronșic",
  "medicatie_actuala": [],
  "evaluare_functionala_initiala": "Presiunea locală pe genunchiul drept și glezna dreaptă este tolerată parțial, însă mișcarea provocată reproduce simptomul descris la volan."
}
